LICENSE
NOTICE
install.json
package.json
pyproject.toml
amazon_sagemaker_sql_editor/__init__.py
amazon_sagemaker_sql_editor/_version.py
amazon_sagemaker_sql_editor/extension.py
amazon_sagemaker_sql_editor/handlers.py
amazon_sagemaker_sql_editor/adapter/adapter_factory.py
amazon_sagemaker_sql_editor/adapter/adapters.py
amazon_sagemaker_sql_editor/cache/__init__.py
amazon_sagemaker_sql_editor/cache/api_cache.py
amazon_sagemaker_sql_editor/data_store/athena/__init__.py
amazon_sagemaker_sql_editor/data_store/athena/adapter.py
amazon_sagemaker_sql_editor/data_store/athena/service.py
amazon_sagemaker_sql_editor/data_store/glue/__init__.py
amazon_sagemaker_sql_editor/data_store/glue/adapter.py
amazon_sagemaker_sql_editor/data_store/redshift/__init__.py
amazon_sagemaker_sql_editor/data_store/redshift/adapter.py
amazon_sagemaker_sql_editor/data_store/redshift/service.py
amazon_sagemaker_sql_editor/data_store/snowflake/__init__.py
amazon_sagemaker_sql_editor/data_store/snowflake/adapter.py
amazon_sagemaker_sql_editor/data_store/snowflake/service.py
amazon_sagemaker_sql_editor/labextension/package.json
amazon_sagemaker_sql_editor/labextension/schemas/@amzn/amazon_sagemaker_sql_editor/dora-side-panel.json
amazon_sagemaker_sql_editor/labextension/schemas/@amzn/amazon_sagemaker_sql_editor/package.json.orig
amazon_sagemaker_sql_editor/labextension/static/18.3cd1c9086d107be4d6aa.js
amazon_sagemaker_sql_editor/labextension/static/18.3cd1c9086d107be4d6aa.js.LICENSE.txt
amazon_sagemaker_sql_editor/labextension/static/285.1e1c6e03719f825e2fab.js
amazon_sagemaker_sql_editor/labextension/static/315.a2d8bea073429d48d652.js
amazon_sagemaker_sql_editor/labextension/static/338.580bd3cf4cffa0f456aa.js
amazon_sagemaker_sql_editor/labextension/static/338.580bd3cf4cffa0f456aa.js.LICENSE.txt
amazon_sagemaker_sql_editor/labextension/static/378.97d19c9d9373933d99d6.js
amazon_sagemaker_sql_editor/labextension/static/388.274e5c9a5e587027d745.js
amazon_sagemaker_sql_editor-0.1.4.dist-info/METADATA
amazon_sagemaker_sql_editor-0.1.4.dist-info/WHEEL
amazon_sagemaker_sql_editor-0.1.4.dist-info/licenses/LICENSE
amazon_sagemaker_sql_editor-0.1.4.dist-info/licenses/NOTICE
amazon_sagemaker_sql_editor-0.1.4.dist-info/RECORD
