Metadata-Version: 2.3
Name: amazon-sagemaker-sql-editor
Version: 0.1.4
Summary: Jupyter extension for SQL editing capabilities within Amazon SageMaker notebooks
Project-URL: Homepage, https://aws.amazon.com/sagemaker/
Author: Amazon
License:                                 Apache License
License-File: LICENSE
License-File: NOTICE
Classifier: Framework :: Jupyter
Classifier: Framework :: Jupyter :: JupyterLab
Classifier: Framework :: Jupyter :: JupyterLab :: 4
Classifier: Framework :: Jupyter :: JupyterLab :: Extensions
Classifier: Framework :: Jupyter :: JupyterLab :: Extensions :: Prebuilt
Classifier: License :: OSI Approved :: BSD License
Classifier: Programming Language :: Python
Classifier: Programming Language :: Python :: 3.8
Classifier: Programming Language :: Python :: 3.9
Classifier: Programming Language :: Python :: 3.10
Classifier: Programming Language :: Python :: 3.11
Classifier: Programming Language :: Python :: 3.12
Requires-Python: >=3.8
Requires-Dist: aiobotocore<3,>=2.7.0
Requires-Dist: amazon-sagemaker-sql-execution<1,>=0.0.7
Requires-Dist: boto3<2,>=1.29.6
Requires-Dist: botocore<2,>=1.31.64
Requires-Dist: diskcache==5.6.*
Requires-Dist: jupyter-server
Requires-Dist: jupyterlab-lsp==5.0.*
Provides-Extra: all
Requires-Dist: amazon-sagemaker-sql-editor[dev,flake8,pydocstyle,pylint,test,twine]; extra == 'all'
Provides-Extra: dev
Requires-Dist: black; extra == 'dev'
Requires-Dist: build; extra == 'dev'
Requires-Dist: hatch; extra == 'dev'
Requires-Dist: twine; extra == 'dev'
Provides-Extra: flake8
Requires-Dist: flake8-future-import==0.4.6; extra == 'flake8'
Requires-Dist: flake8==4.0.1; extra == 'flake8'
Provides-Extra: pydocstyle
Requires-Dist: pydocstyle==6.1.1; extra == 'pydocstyle'
Provides-Extra: pylint
Requires-Dist: astroid==2.4.2; extra == 'pylint'
Requires-Dist: pylint==2.6.2; extra == 'pylint'
Provides-Extra: test
Requires-Dist: coverage; extra == 'test'
Requires-Dist: parameterized; extra == 'test'
Requires-Dist: pytest; extra == 'test'
Requires-Dist: pytest-asyncio; extra == 'test'
Requires-Dist: pytest-cov; extra == 'test'
Requires-Dist: pytest-timeout; extra == 'test'
Requires-Dist: tox==4.11.4; extra == 'test'
Provides-Extra: twine
Requires-Dist: packaging; extra == 'twine'
Requires-Dist: twine==3.8.0; extra == 'twine'
